geo-pass
setup.cfg
setup.py
geo_pass/__init__.py
geo_pass/api.py
geo_pass/metadata.json
geo_pass.egg-info/PKG-INFO
geo_pass.egg-info/SOURCES.txt
geo_pass.egg-info/dependency_links.txt
geo_pass.egg-info/requires.txt
geo_pass.egg-info/top_level.txt