Metadata-Version: 1.1
Name: geo-pass
Version: 0.2.8
Summary: A REST API for geographic elements through Overpass and OpenStreetMap
Home-page: https://github.com/fserena/geo-pass
Author: Fernando Serena
Author-email: fserena@fi.upm.es
License: Apache 2
Download-URL: https://github.com/fserena/geo-pass/tarball/0.2.8
Keywords: overpass,osm
Platform: UNKNOWN
